refcliq/__init__.py
refcliq/bibtex.py
refcliq/citations.py
refcliq/geocoding.py
refcliq/preprocess.py
refcliq/util.py
refcliq/template/asset-manifest.json
refcliq/template/chevron-bottom.svg
refcliq/template/chevron-left.svg
refcliq/template/chevron-right.svg
refcliq/template/chevron-top.svg
refcliq/template/favicon.ico
refcliq/template/index.html
refcliq/template/manifest.json
refcliq/template/precache-manifest.99c418ed6a0233374c7518d6e58dcde3.js
refcliq/template/service-worker.js
refcliq/template/static/css/2.b4a16772.chunk.css
refcliq/template/static/css/2.b4a16772.chunk.css.map
refcliq/template/static/css/main.e4a099b4.chunk.css
refcliq/template/static/css/main.e4a099b4.chunk.css.map
refcliq/template/static/js/2.98aafae4.chunk.js
refcliq/template/static/js/2.98aafae4.chunk.js.LICENSE.txt
refcliq/template/static/js/2.98aafae4.chunk.js.map
refcliq/template/static/js/main.5135dcd0.chunk.js
refcliq/template/static/js/main.5135dcd0.chunk.js.map
refcliq/template/static/js/runtime-main.f312520c.js
refcliq/template/static/js/runtime-main.f312520c.js.map
refcliq-0.1.12.data/scripts/rc_cluster.py
refcliq-0.1.12.data/scripts/rc_vis.py
refcliq-0.1.12.dist-info/METADATA
refcliq-0.1.12.dist-info/WHEEL
refcliq-0.1.12.dist-info/top_level.txt
refcliq-0.1.12.dist-info/RECORD
