Metadata-Version: 2.1
Name: refcliq
Version: 0.1.12
Summary: Community analysis in bibliographical references
Home-page: https://github.com/fabioasdias/RefCliq
Author: Fabio Dias
Author-email: fabio.dias@gmail.com
License: UNKNOWN
Platform: UNKNOWN
Classifier: Programming Language :: Python :: 3
Classifier: License :: OSI Approved :: MIT License
Classifier: Operating System :: OS Independent
Requires-Dist: fuzzywuzzy[speedup] (==0.18.0)
Requires-Dist: googlemaps (==3.0.2)
Requires-Dist: nltk (==3.4)
Requires-Dist: numpy (==1.16.2)
Requires-Dist: pybtex (==0.22.2)
Requires-Dist: python-louvain (==0.13)
Requires-Dist: scikit-learn (==0.20.3)
Requires-Dist: titlecase (==0.12.0)
Requires-Dist: tqdm (==4.31.1)
